exact_cover/__init__.py
exact_cover/error.py
exact_cover/helpers.py
exact_cover/io.py
exact_cover/wrapper.py
exact_cover_impl.cp39-win_amd64.pyd
exact_cover-1.5.0.dist-info/entry_points.txt
exact_cover-1.5.0.dist-info/LICENSE
exact_cover-1.5.0.dist-info/METADATA
exact_cover-1.5.0.dist-info/WHEEL
exact_cover-1.5.0.dist-info/RECORD
