Metadata-Version: 2.1
Name: exact-cover
Version: 1.5.0
Summary: Solve exact cover problems
Home-page: https://github.com/jwg4/exact_cover
License: GPL-2.0-only
Author: Moy Easwaran
Maintainer: Jack Grahl
Maintainer-email: jack.grahl@gmail.com
Requires-Python: >=3.7,<4.0
Classifier: License :: OSI Approved :: GNU General Public License v2 (GPLv2)
Classifier: Programming Language :: Python :: 3
Classifier: Programming Language :: Python :: 3.7
Classifier: Programming Language :: Python :: 3.8
Classifier: Programming Language :: Python :: 3.9
Classifier: Programming Language :: Python :: 3.10
Classifier: Programming Language :: Python :: 3.11
Requires-Dist: numpy (>=1.14) ; python_version == "3.7"
Requires-Dist: numpy (>=1.17) ; python_version == "3.8"
Requires-Dist: numpy (>=1.19) ; python_version == "3.9"
Requires-Dist: numpy (>=1.21) ; python_version == "3.10"
Requires-Dist: numpy (>=1.23) ; python_version == "3.11"
Requires-Dist: numpy (>=1.24) ; python_version >= "3.12"
Requires-Dist: setuptools (>=51.1.2)
Project-URL: Repository, https://github.com/jwg4/exact_cover
